[
  {
    "bridge_balance_mohm": null,
    "id": 593322990,
    "leak_pa": null,
    "num_spikes": null,
    "peak_deflection": null,
    "post_noise_rms_mv": null,
    "post_vm_mv": null,
    "pre_noise_rms_mv": null,
    "pre_vm_mv": null,
    "slow_noise_rms_mv": null,
    "slow_vm_mv": null,
    "specimen_id": 593312584,
    "stimulus_absolute_amplitude": null,
    "stimulus_description": "EXTPRSCHEK150209[0]",
    "stimulus_duration": null,
    "stimulus_interval": null,
    "stimulus_name": "Test",
    "stimulus_relative_amplitude": 0.5,
    "stimulus_start_time": null,
    "stimulus_units": "mV",
    "sweep_number": 53,
    "vm_delta_mv": null
  },
  {
    "bridge_balance_mohm": 10.9890108108521,
    "id": 593322852,
    "leak_pa": -11.0161447525024,
    "num_spikes": 3,
    "peak_deflection": null,
    "post_noise_rms_mv": 0.0413864217698574,
    "post_vm_mv": -67.4335174560547,
    "pre_noise_rms_mv": 0.0408249832689762,
    "pre_vm_mv": -67.4496383666992,
    "slow_noise_rms_mv": 0.206396013498306,
    "slow_vm_mv": -67.4496383666992,
    "specimen_id": 593312584,
    "stimulus_absolute_amplitude": 230.000005152498,
    "stimulus_description": "C2SSTRIPLE150429[1]",
    "stimulus_duration": 0.32898,
    "stimulus_interval": 0.163,
    "stimulus_name": "Short Square - Triple",
    "stimulus_relative_amplitude": 10.0,
    "stimulus_start_time": 2.02,
    "stimulus_units": "pA",
    "sweep_number": 72,
    "vm_delta_mv": 0.0161209106445312
  },
  {
    "bridge_balance_mohm": 10.9890108108521,
    "id": 593322928,
    "leak_pa": 3.9886040687561,
    "num_spikes": null,
    "peak_deflection": null,
    "post_noise_rms_mv": 0.0401463843882084,
    "post_vm_mv": -67.4525146484375,
    "pre_noise_rms_mv": 0.0382180660963058,
    "pre_vm_mv": -67.383430480957,
    "slow_noise_rms_mv": 0.180506959557533,
    "slow_vm_mv": -67.383430480957,
    "specimen_id": 593312584,
    "stimulus_absolute_amplitude": 100.000001335143,
    "stimulus_description": "C1SSCOARSE150112[0]",
    "stimulus_duration": 0.00298,
    "stimulus_interval": null,
    "stimulus_name": "Short Square",
    "stimulus_relative_amplitude": 10.0,
    "stimulus_start_time": 1.02,
    "stimulus_units": "pA",
    "sweep_number": 7,
    "vm_delta_mv": 0.0690841674804688
  },
  {
    "bridge_balance_mohm": 10.9890108108521,
    "id": 593322973,
    "leak_pa": 2.21589112281799,
    "num_spikes": 1,
    "peak_deflection": null,
    "post_noise_rms_mv": 0.0377402417361736,
    "post_vm_mv": -68.7176666259766,
    "pre_noise_rms_mv": 0.039849366992712,
    "pre_vm_mv": -68.2920837402344,
    "slow_noise_rms_mv": 0.11422161757946,
    "slow_vm_mv": -68.2920837402344,
    "specimen_id": 593312584,
    "stimulus_absolute_amplitude": 230.000005152498,
    "stimulus_description": "C1SSFINEST150112[0]",
    "stimulus_duration": 0.00298,
    "stimulus_interval": null,
    "stimulus_name": "Short Square",
    "stimulus_relative_amplitude": 10.0,
    "stimulus_start_time": 1.02,
    "stimulus_units": "pA",
    "sweep_number": 20,
    "vm_delta_mv": 0.425582885742188
  },
  {
    "bridge_balance_mohm": 10.9890108108521,
    "id": 593322912,
    "leak_pa": -11.0161447525024,
    "num_spikes": 3,
    "peak_deflection": null,
    "post_noise_rms_mv": 0.0520802214741707,
    "post_vm_mv": -67.9191665649414,
    "pre_noise_rms_mv": 0.0376148298382759,
    "pre_vm_mv": -67.864372253418,
    "slow_noise_rms_mv": 0.130364418029785,
    "slow_vm_mv": -67.864372253418,
    "specimen_id": 593312584,
    "stimulus_absolute_amplitude": 230.000005152498,
    "stimulus_description": "C2SSTRIPLE150429[4]",
    "stimulus_duration": 0.04898,
    "stimulus_interval": 0.023,
    "stimulus_name": "Short Square - Triple",
    "stimulus_relative_amplitude": 10.0,
    "stimulus_start_time": 2.02,
    "stimulus_units": "pA",
    "sweep_number": 82,
    "vm_delta_mv": 0.0547943115234375
  },
  {
    "bridge_balance_mohm": 10.9890108108521,
    "id": 593322840,
    "leak_pa": -11.0161447525024,
    "num_spikes": 3,
    "peak_deflection": null,
    "post_noise_rms_mv": 0.0367988832294941,
    "post_vm_mv": -67.4871597290039,
    "pre_noise_rms_mv": 0.0435523465275764,
    "pre_vm_mv": -67.8234710693359,
    "slow_noise_rms_mv": 0.208158388733864,
    "slow_vm_mv": -67.8234710693359,
    "specimen_id": 593312584,
    "stimulus_absolute_amplitude": 230.000005152498,
    "stimulus_description": "C2SSTRIPLE150429[0]",
    "stimulus_duration": 0.64898,
    "stimulus_interval": 0.323,
    "stimulus_name": "Short Square - Triple",
    "stimulus_relative_amplitude": 10.0,
    "stimulus_start_time": 2.02,
    "stimulus_units": "pA",
    "sweep_number": 78,
    "vm_delta_mv": 0.336311340332031
  },
  {
    "bridge_balance_mohm": 10.9890108108521,
    "id": 593322826,
    "leak_pa": 0.506489396095276,
    "num_spikes": 12,
    "peak_deflection": null,
    "post_noise_rms_mv": 0.031225673854351,
    "post_vm_mv": -68.416877746582,
    "pre_noise_rms_mv": 0.0411563813686371,
    "pre_vm_mv": -68.1298980712891,
    "slow_noise_rms_mv": 0.142709761857986,
    "slow_vm_mv": -68.1298980712891,
    "specimen_id": 593312584,
    "stimulus_absolute_amplitude": 79.9999996803358,
    "stimulus_description": "C1LSFINEST150112[0]",
    "stimulus_duration": 0.99998,
    "stimulus_interval": null,
    "stimulus_name": "Long Square",
    "stimulus_relative_amplitude": 10.0,
    "stimulus_start_time": 1.02,
    "stimulus_units": "pA",
    "sweep_number": 42,
    "vm_delta_mv": 0.286979675292969
  },
  {
    "bridge_balance_mohm": 10.9890108108521,
    "id": 593322872,
    "leak_pa": -11.0161447525024,
    "num_spikes": 3,
    "peak_deflection": null,
    "post_noise_rms_mv": 0.0412595719099045,
    "post_vm_mv": -68.1207275390625,
    "pre_noise_rms_mv": 0.040041409432888,
    "pre_vm_mv": -68.1179885864258,
    "slow_noise_rms_mv": 0.248216152191162,
    "slow_vm_mv": -68.1179885864258,
    "specimen_id": 593312584,
    "stimulus_absolute_amplitude": 230.000005152498,
    "stimulus_description": "C2SSTRIPLE150429[3]",
    "stimulus_duration": 0.08898,
    "stimulus_interval": 0.043,
    "stimulus_name": "Short Square - Triple",
    "stimulus_relative_amplitude": 10.0,
    "stimulus_start_time": 2.02,
    "stimulus_units": "pA",
    "sweep_number": 67,
    "vm_delta_mv": 0.00273895263671875
  },
  {
    "bridge_balance_mohm": 10.9890108108521,
    "id": 593322848,
    "leak_pa": -11.0161447525024,
    "num_spikes": 3,
    "peak_deflection": null,
    "post_noise_rms_mv": 0.029037581756711,
    "post_vm_mv": -68.1189651489258,
    "pre_noise_rms_mv": 0.0321784727275372,
    "pre_vm_mv": -67.5938568115234,
    "slow_noise_rms_mv": 0.157261341810226,
    "slow_vm_mv": -67.5938568115234,
    "specimen_id": 593312584,
    "stimulus_absolute_amplitude": 230.000005152498,
    "stimulus_description": "C2SSTRIPLE150429[3]",
    "stimulus_duration": 0.08898,
    "stimulus_interval": 0.043,
    "stimulus_name": "Short Square - Triple",
    "stimulus_relative_amplitude": 10.0,
    "stimulus_start_time": 2.02,
    "stimulus_units": "pA",
    "sweep_number": 74,
    "vm_delta_mv": 0.525108337402344
  },
  {
    "bridge_balance_mohm": 10.9890108108521,
    "id": 593322854,
    "leak_pa": -11.0161447525024,
    "num_spikes": 3,
    "peak_deflection": null,
    "post_noise_rms_mv": 0.0386391058564186,
    "post_vm_mv": -67.3190002441406,
    "pre_noise_rms_mv": 0.0471389815211296,
    "pre_vm_mv": -67.3180923461914,
    "slow_noise_rms_mv": 0.283062040805817,
    "slow_vm_mv": -67.3180923461914,
    "specimen_id": 593312584,
    "stimulus_absolute_amplitude": 230.000005152498,
    "stimulus_description": "C2SSTRIPLE150429[2]",
    "stimulus_duration": 0.16898,
    "stimulus_interval": 0.083,
    "stimulus_name": "Short Square - Triple",
    "stimulus_relative_amplitude": 10.0,
    "stimulus_start_time": 2.02,
    "stimulus_units": "pA",
    "sweep_number": 73,
    "vm_delta_mv": 0.00090789794921875
  },
  {
    "bridge_balance_mohm": 10.9890108108521,
    "id": 593322828,
    "leak_pa": 0.506489396095276,
    "num_spikes": 13,
    "peak_deflection": null,
    "post_noise_rms_mv": 0.0369318686425686,
    "post_vm_mv": -68.7877426147461,
    "pre_noise_rms_mv": 0.0377615578472614,
    "pre_vm_mv": -68.1594772338867,
    "slow_noise_rms_mv": 0.369429469108582,
    "slow_vm_mv": -68.1594772338867,
    "specimen_id": 593312584,
    "stimulus_absolute_amplitude": 79.9999996803358,
    "stimulus_description": "C1LSFINEST150112[0]",
    "stimulus_duration": 0.99998,
    "stimulus_interval": null,
    "stimulus_name": "Long Square",
    "stimulus_relative_amplitude": 10.0,
    "stimulus_start_time": 1.02,
    "stimulus_units": "pA",
    "sweep_number": 41,
    "vm_delta_mv": 0.628265380859375
  },
  {
    "bridge_balance_mohm": 10.9890108108521,
    "id": 593322984,
    "leak_pa": -2.78569149971008,
    "num_spikes": 44,
    "peak_deflection": null,
    "post_noise_rms_mv": 0.0333758592605591,
    "post_vm_mv": -68.1834182739258,
    "pre_noise_rms_mv": 0.0374641753733158,
    "pre_vm_mv": -67.7840805053711,
    "slow_noise_rms_mv": 0.158785790205002,
    "slow_vm_mv": -67.7840805053711,
    "specimen_id": 593312584,
    "stimulus_absolute_amplitude": 94.2499966960497,
    "stimulus_description": "C1NSSEED_2150112[0]",
    "stimulus_duration": 18.99998,
    "stimulus_interval": 8.0,
    "stimulus_name": "Noise 2",
    "stimulus_relative_amplitude": 10.0,
    "stimulus_start_time": 2.02,
    "stimulus_units": "pA",
    "sweep_number": 50,
    "vm_delta_mv": 0.399337768554688
  },
  {
    "bridge_balance_mohm": 10.9890108108521,
    "id": 593322932,
    "leak_pa": 2.72238039970398,
    "num_spikes": 10,
    "peak_deflection": null,
    "post_noise_rms_mv": null,
    "post_vm_mv": null,
    "pre_noise_rms_mv": 0.0418852120637894,
    "pre_vm_mv": -67.8161163330078,
    "slow_noise_rms_mv": 0.109599709510803,
    "slow_vm_mv": -67.8161163330078,
    "specimen_id": 593312584,
    "stimulus_absolute_amplitude": 800.000010681146,
    "stimulus_description": "C1RP25PR1S141203[0]",
    "stimulus_duration": 31.99748,
    "stimulus_interval": null,
    "stimulus_name": "Ramp",
    "stimulus_relative_amplitude": 10.0,
    "stimulus_start_time": 1.0225,
    "stimulus_units": "pA",
    "sweep_number": 5,
    "vm_delta_mv": null
  },
  {
    "bridge_balance_mohm": 10.9890108108521,
    "id": 593322820,
    "leak_pa": -2.0259575843811,
    "num_spikes": 42,
    "peak_deflection": null,
    "post_noise_rms_mv": 0.0329037569463253,
    "post_vm_mv": -68.4947967529297,
    "pre_noise_rms_mv": 0.0355658121407032,
    "pre_vm_mv": -67.9179382324219,
    "slow_noise_rms_mv": 0.177968516945839,
    "slow_vm_mv": -67.9179382324219,
    "specimen_id": 593312584,
    "stimulus_absolute_amplitude": 92.7500021230543,
    "stimulus_description": "C1NSSEED_1150112[0]",
    "stimulus_duration": 18.99998,
    "stimulus_interval": 8.0,
    "stimulus_name": "Noise 1",
    "stimulus_relative_amplitude": 10.0,
    "stimulus_start_time": 2.02,
    "stimulus_units": "pA",
    "sweep_number": 49,
    "vm_delta_mv": 0.576858520507812
  },
  {
    "bridge_balance_mohm": 10.9890108108521,
    "id": 593322976,
    "leak_pa": 2.21589112281799,
    "num_spikes": null,
    "peak_deflection": -103.812507629395,
    "post_noise_rms_mv": 0.0437465272843838,
    "post_vm_mv": -66.8913803100586,
    "pre_noise_rms_mv": 0.0351108871400356,
    "pre_vm_mv": -67.6822280883789,
    "slow_noise_rms_mv": 0.20357121527195,
    "slow_vm_mv": -67.6822280883789,
    "specimen_id": 593312584,
    "stimulus_absolute_amplitude": -69.9999988529321,
    "stimulus_description": "C1LSCOARSE150216[2]",
    "stimulus_duration": 0.99998,
    "stimulus_interval": null,
    "stimulus_name": "Long Square",
    "stimulus_relative_amplitude": 10.0,
    "stimulus_start_time": 1.02,
    "stimulus_units": "pA",
    "sweep_number": 23,
    "vm_delta_mv": 0.790847778320312
  },
  {
    "bridge_balance_mohm": 10.9890108108521,
    "id": 593322960,
    "leak_pa": 1.26622343063354,
    "num_spikes": null,
    "peak_deflection": -51.28125,
    "post_noise_rms_mv": 0.0304316133260727,
    "post_vm_mv": -68.0349273681641,
    "pre_noise_rms_mv": 0.0293158181011677,
    "pre_vm_mv": -68.1815414428711,
    "slow_noise_rms_mv": 0.222440958023071,
    "slow_vm_mv": -68.1815414428711,
    "specimen_id": 593312584,
    "stimulus_absolute_amplitude": 29.9999990127642,
    "stimulus_description": "C1LSCOARSE150216[7]",
    "stimulus_duration": 0.99998,
    "stimulus_interval": null,
    "stimulus_name": "Long Square",
    "stimulus_relative_amplitude": 10.0,
    "stimulus_start_time": 1.02,
    "stimulus_units": "pA",
    "sweep_number": 28,
    "vm_delta_mv": 0.146614074707031
  },
  {
    "bridge_balance_mohm": 10.9890108108521,
    "id": 593322978,
    "leak_pa": 2.21589112281799,
    "num_spikes": null,
    "peak_deflection": -112.53125,
    "post_noise_rms_mv": 0.0440446138381958,
    "post_vm_mv": -68.041374206543,
    "pre_noise_rms_mv": 0.0413815900683403,
    "pre_vm_mv": -67.9903717041016,
    "slow_noise_rms_mv": 0.138793125748634,
    "slow_vm_mv": -67.9903717041016,
    "specimen_id": 593312584,
    "stimulus_absolute_amplitude": -90.0000005077395,
    "stimulus_description": "C1LSCOARSE150216[1]",
    "stimulus_duration": 0.99998,
    "stimulus_interval": null,
    "stimulus_name": "Long Square",
    "stimulus_relative_amplitude": 10.0,
    "stimulus_start_time": 1.02,
    "stimulus_units": "pA",
    "sweep_number": 22,
    "vm_delta_mv": 0.0510025024414062
  },
  {
    "bridge_balance_mohm": 10.9890108108521,
    "id": 593322926,
    "leak_pa": 3.54542565345764,
    "num_spikes": 9,
    "peak_deflection": null,
    "post_noise_rms_mv": null,
    "post_vm_mv": null,
    "pre_noise_rms_mv": 0.0381741560995579,
    "pre_vm_mv": -67.6250534057617,
    "slow_noise_rms_mv": 0.110198698937893,
    "slow_vm_mv": -67.6250534057617,
    "specimen_id": 593312584,
    "stimulus_absolute_amplitude": 800.000010681146,
    "stimulus_description": "C1RP25PR1S141203[0]",
    "stimulus_duration": 31.99748,
    "stimulus_interval": null,
    "stimulus_name": "Ramp",
    "stimulus_relative_amplitude": 10.0,
    "stimulus_start_time": 1.0225,
    "stimulus_units": "pA",
    "sweep_number": 6,
    "vm_delta_mv": null
  },
  {
    "bridge_balance_mohm": 10.9890108108521,
    "id": 593322896,
    "leak_pa": 2.21589112281799,
    "num_spikes": 1,
    "peak_deflection": null,
    "post_noise_rms_mv": 0.0387201420962811,
    "post_vm_mv": -68.5867004394531,
    "pre_noise_rms_mv": 0.0341442376375198,
    "pre_vm_mv": -68.5257873535156,
    "slow_noise_rms_mv": 0.112356528639793,
    "slow_vm_mv": -68.5257873535156,
    "specimen_id": 593312584,
    "stimulus_absolute_amplitude": 230.000005152498,
    "stimulus_description": "C1SSFINEST150112[0]",
    "stimulus_duration": 0.00298,
    "stimulus_interval": null,
    "stimulus_name": "Short Square",
    "stimulus_relative_amplitude": 10.0,
    "stimulus_start_time": 1.02,
    "stimulus_units": "pA",
    "sweep_number": 18,
    "vm_delta_mv": 0.0609130859375
  },
  {
    "bridge_balance_mohm": 10.9890108108521,
    "id": 593322842,
    "leak_pa": -11.0161447525024,
    "num_spikes": 3,
    "peak_deflection": null,
    "post_noise_rms_mv": 0.0457122065126896,
    "post_vm_mv": -67.497200012207,
    "pre_noise_rms_mv": 0.0398474000394344,
    "pre_vm_mv": -67.0520172119141,
    "slow_noise_rms_mv": 0.283825635910034,
    "slow_vm_mv": -67.0520172119141,
    "specimen_id": 593312584,
    "stimulus_absolute_amplitude": 230.000005152498,
    "stimulus_description": "C2SSTRIPLE150429[1]",
    "stimulus_duration": 0.32898,
    "stimulus_interval": 0.163,
    "stimulus_name": "Short Square - Triple",
    "stimulus_relative_amplitude": 10.0,
    "stimulus_start_time": 2.02,
    "stimulus_units": "pA",
    "sweep_number": 79,
    "vm_delta_mv": 0.445182800292969
  },
  {
    "bridge_balance_mohm": 10.9890108108521,
    "id": 593322944,
    "leak_pa": 1.26622343063354,
    "num_spikes": 30,
    "peak_deflection": null,
    "post_noise_rms_mv": 0.0470372624695301,
    "post_vm_mv": -68.8924179077148,
    "pre_noise_rms_mv": 0.0354868173599243,
    "pre_vm_mv": -67.9905471801758,
    "slow_noise_rms_mv": 0.177037075161934,
    "slow_vm_mv": -67.9905471801758,
    "specimen_id": 593312584,
    "stimulus_absolute_amplitude": 129.99999687846,
    "stimulus_description": "C1LSCOARSE150216[12]",
    "stimulus_duration": 0.99998,
    "stimulus_interval": null,
    "stimulus_name": "Long Square",
    "stimulus_relative_amplitude": 10.0,
    "stimulus_start_time": 1.02,
    "stimulus_units": "pA",
    "sweep_number": 33,
    "vm_delta_mv": 0.901870727539062
  },
  {
    "bridge_balance_mohm": 10.9890108108521,
    "id": 593322934,
    "leak_pa": 3.9886040687561,
    "num_spikes": null,
    "peak_deflection": null,
    "post_noise_rms_mv": 0.0419071018695831,
    "post_vm_mv": -67.1484909057617,
    "pre_noise_rms_mv": 0.0432943850755692,
    "pre_vm_mv": -67.225471496582,
    "slow_noise_rms_mv": 0.163479134440422,
    "slow_vm_mv": -67.225471496582,
    "specimen_id": 593312584,
    "stimulus_absolute_amplitude": 200.000002670286,
    "stimulus_description": "C1SSCOARSE150112[1]",
    "stimulus_duration": 0.00298,
    "stimulus_interval": null,
    "stimulus_name": "Short Square",
    "stimulus_relative_amplitude": 10.0,
    "stimulus_start_time": 1.02,
    "stimulus_units": "pA",
    "sweep_number": 8,
    "vm_delta_mv": 0.0769805908203125
  },
  {
    "bridge_balance_mohm": 10.9890108108521,
    "id": 593322844,
    "leak_pa": -11.0161447525024,
    "num_spikes": 3,
    "peak_deflection": null,
    "post_noise_rms_mv": 0.0373508222401142,
    "post_vm_mv": -68.2855529785156,
    "pre_noise_rms_mv": 0.0423562861979008,
    "pre_vm_mv": -67.6885223388672,
    "slow_noise_rms_mv": 0.170636668801308,
    "slow_vm_mv": -67.6885223388672,
    "specimen_id": 593312584,
    "stimulus_absolute_amplitude": 230.000005152498,
    "stimulus_description": "C2SSTRIPLE150429[5]",
    "stimulus_duration": 0.02898,
    "stimulus_interval": 0.013,
    "stimulus_name": "Short Square - Triple",
    "stimulus_relative_amplitude": 10.0,
    "stimulus_start_time": 2.02,
    "stimulus_units": "pA",
    "sweep_number": 76,
    "vm_delta_mv": 0.597030639648438
  },
  {
    "bridge_balance_mohm": 10.9890108108521,
    "id": 593322946,
    "leak_pa": 1.26622343063354,
    "num_spikes": 11,
    "peak_deflection": null,
    "post_noise_rms_mv": 0.0360705405473709,
    "post_vm_mv": -68.5641784667969,
    "pre_noise_rms_mv": 0.0484130419790745,
    "pre_vm_mv": -68.3246841430664,
    "slow_noise_rms_mv": 0.206545874476433,
    "slow_vm_mv": -68.3246841430664,
    "specimen_id": 593312584,
    "stimulus_absolute_amplitude": 69.9999988529321,
    "stimulus_description": "C1LSCOARSE150216[9]",
    "stimulus_duration": 0.99998,
    "stimulus_interval": null,
    "stimulus_name": "Long Square",
    "stimulus_relative_amplitude": 10.0,
    "stimulus_start_time": 1.02,
    "stimulus_units": "pA",
    "sweep_number": 30,
    "vm_delta_mv": 0.239494323730469
  },
  {
    "bridge_balance_mohm": null,
    "id": 593322906,
    "leak_pa": null,
    "num_spikes": null,
    "peak_deflection": null,
    "post_noise_rms_mv": null,
    "post_vm_mv": null,
    "pre_noise_rms_mv": null,
    "pre_vm_mv": null,
    "slow_noise_rms_mv": null,
    "slow_vm_mv": null,
    "specimen_id": 593312584,
    "stimulus_absolute_amplitude": null,
    "stimulus_description": "EXTPEXPEND141203[0]",
    "stimulus_duration": null,
    "stimulus_interval": null,
    "stimulus_name": "Test",
    "stimulus_relative_amplitude": 0.5,
    "stimulus_start_time": null,
    "stimulus_units": "mV",
    "sweep_number": 85,
    "vm_delta_mv": null
  },
  {
    "bridge_balance_mohm": 10.9890108108521,
    "id": 593322966,
    "leak_pa": 1.26622343063354,
    "num_spikes": null,
    "peak_deflection": -61.5937538146973,
    "post_noise_rms_mv": 0.0389733426272869,
    "post_vm_mv": -68.032585144043,
    "pre_noise_rms_mv": 0.0431330278515816,
    "pre_vm_mv": -68.1392593383789,
    "slow_noise_rms_mv": 0.171366959810257,
    "slow_vm_mv": -68.1392593383789,
    "specimen_id": 593312584,
    "stimulus_absolute_amplitude": 9.99999996004197,
    "stimulus_description": "C1LSCOARSE150216[6]",
    "stimulus_duration": 0.99998,
    "stimulus_interval": null,
    "stimulus_name": "Long Square",
    "stimulus_relative_amplitude": 10.0,
    "stimulus_start_time": 1.02,
    "stimulus_units": "pA",
    "sweep_number": 27,
    "vm_delta_mv": 0.106674194335938
  },
  {
    "bridge_balance_mohm": 10.9890108108521,
    "id": 593322908,
    "leak_pa": -11.0161447525024,
    "num_spikes": 3,
    "peak_deflection": null,
    "post_noise_rms_mv": 0.0430999435484409,
    "post_vm_mv": -67.8906097412109,
    "pre_noise_rms_mv": 0.0386252887547016,
    "pre_vm_mv": -67.5483016967773,
    "slow_noise_rms_mv": 0.10490095615387,
    "slow_vm_mv": -67.5483016967773,
    "specimen_id": 593312584,
    "stimulus_absolute_amplitude": 230.000005152498,
    "stimulus_description": "C2SSTRIPLE150429[6]",
    "stimulus_duration": 0.01898,
    "stimulus_interval": 0.008,
    "stimulus_name": "Short Square - Triple",
    "stimulus_relative_amplitude": 10.0,
    "stimulus_start_time": 2.02,
    "stimulus_units": "pA",
    "sweep_number": 84,
    "vm_delta_mv": 0.342308044433594
  },
  {
    "bridge_balance_mohm": 10.9890108108521,
    "id": 593322914,
    "leak_pa": -11.0161447525024,
    "num_spikes": 3,
    "peak_deflection": null,
    "post_noise_rms_mv": 0.0431005135178566,
    "post_vm_mv": -67.6903228759766,
    "pre_noise_rms_mv": 0.0390095636248589,
    "pre_vm_mv": -67.5850067138672,
    "slow_noise_rms_mv": 0.353068083524704,
    "slow_vm_mv": -67.5850067138672,
    "specimen_id": 593312584,
    "stimulus_absolute_amplitude": 230.000005152498,
    "stimulus_description": "C2SSTRIPLE150429[3]",
    "stimulus_duration": 0.08898,
    "stimulus_interval": 0.043,
    "stimulus_name": "Short Square - Triple",
    "stimulus_relative_amplitude": 10.0,
    "stimulus_start_time": 2.02,
    "stimulus_units": "pA",
    "sweep_number": 81,
    "vm_delta_mv": 0.105316162109375
  },
  {
    "bridge_balance_mohm": 10.9890108108521,
    "id": 593322930,
    "leak_pa": 0.759734094142914,
    "num_spikes": 8,
    "peak_deflection": null,
    "post_noise_rms_mv": null,
    "post_vm_mv": null,
    "pre_noise_rms_mv": 0.0398472137749195,
    "pre_vm_mv": -68.5248031616211,
    "slow_noise_rms_mv": 0.12231332808733,
    "slow_vm_mv": -68.5248031616211,
    "specimen_id": 593312584,
    "stimulus_absolute_amplitude": 800.000010681146,
    "stimulus_description": "C1RP25PR1S141203[0]",
    "stimulus_duration": 31.99748,
    "stimulus_interval": null,
    "stimulus_name": "Ramp",
    "stimulus_relative_amplitude": 10.0,
    "stimulus_start_time": 1.0225,
    "stimulus_units": "pA",
    "sweep_number": 4,
    "vm_delta_mv": null
  },
  {
    "bridge_balance_mohm": null,
    "id": 593322924,
    "leak_pa": null,
    "num_spikes": null,
    "peak_deflection": null,
    "post_noise_rms_mv": null,
    "post_vm_mv": null,
    "pre_noise_rms_mv": null,
    "pre_vm_mv": null,
    "slow_noise_rms_mv": null,
    "slow_vm_mv": null,
    "specimen_id": 593312584,
    "stimulus_absolute_amplitude": null,
    "stimulus_description": "EXTPINBATH141203[0]",
    "stimulus_duration": null,
    "stimulus_interval": null,
    "stimulus_name": "Test",
    "stimulus_relative_amplitude": 0.5,
    "stimulus_start_time": null,
    "stimulus_units": "mV",
    "sweep_number": 1,
    "vm_delta_mv": null
  },
  {
    "bridge_balance_mohm": 10.9890108108521,
    "id": 593322971,
    "leak_pa": 2.21589112281799,
    "num_spikes": null,
    "peak_deflection": -121.750007629395,
    "post_noise_rms_mv": 0.0387876369059086,
    "post_vm_mv": -68.2138519287109,
    "pre_noise_rms_mv": 0.0383847057819366,
    "pre_vm_mv": -68.3066329956055,
    "slow_noise_rms_mv": 0.167738139629364,
    "slow_vm_mv": -68.3066329956055,
    "specimen_id": 593312584,
    "stimulus_absolute_amplitude": -110.000002162547,
    "stimulus_description": "C1LSCOARSE150216[0]",
    "stimulus_duration": 0.99998,
    "stimulus_interval": null,
    "stimulus_name": "Long Square",
    "stimulus_relative_amplitude": 10.0,
    "stimulus_start_time": 1.02,
    "stimulus_units": "pA",
    "sweep_number": 21,
    "vm_delta_mv": 0.0927810668945312
  },
  {
    "bridge_balance_mohm": 10.9890108108521,
    "id": 593322958,
    "leak_pa": 1.26622343063354,
    "num_spikes": 2,
    "peak_deflection": null,
    "post_noise_rms_mv": 0.0389444343745708,
    "post_vm_mv": -68.6564178466797,
    "pre_noise_rms_mv": 0.0408138670027256,
    "pre_vm_mv": -68.070068359375,
    "slow_noise_rms_mv": 0.154565885663033,
    "slow_vm_mv": -68.070068359375,
    "specimen_id": 593312584,
    "stimulus_absolute_amplitude": 50.0000006675716,
    "stimulus_description": "C1LSCOARSE150216[8]",
    "stimulus_duration": 0.99998,
    "stimulus_interval": null,
    "stimulus_name": "Long Square",
    "stimulus_relative_amplitude": 10.0,
    "stimulus_start_time": 1.02,
    "stimulus_units": "pA",
    "sweep_number": 29,
    "vm_delta_mv": 0.586349487304688
  },
  {
    "bridge_balance_mohm": 10.9890108108521,
    "id": 593322890,
    "leak_pa": 2.21589112281799,
    "num_spikes": 1,
    "peak_deflection": null,
    "post_noise_rms_mv": 0.0389759689569473,
    "post_vm_mv": -68.4440231323242,
    "pre_noise_rms_mv": 0.0422343946993351,
    "pre_vm_mv": -68.1101226806641,
    "slow_noise_rms_mv": 0.148678943514824,
    "slow_vm_mv": -68.1101226806641,
    "specimen_id": 593312584,
    "stimulus_absolute_amplitude": 220.000004325094,
    "stimulus_description": "C1SSFINEST150112[0]",
    "stimulus_duration": 0.00298,
    "stimulus_interval": null,
    "stimulus_name": "Short Square",
    "stimulus_relative_amplitude": 10.0,
    "stimulus_start_time": 1.02,
    "stimulus_units": "pA",
    "sweep_number": 11,
    "vm_delta_mv": 0.333900451660156
  },
  {
    "bridge_balance_mohm": 10.9890108108521,
    "id": 593322938,
    "leak_pa": 0.506489396095276,
    "num_spikes": 1,
    "peak_deflection": null,
    "post_noise_rms_mv": 0.0418732315301895,
    "post_vm_mv": -67.6368255615234,
    "pre_noise_rms_mv": 0.0406107567250729,
    "pre_vm_mv": -67.790153503418,
    "slow_noise_rms_mv": 0.15040323138237,
    "slow_vm_mv": -67.790153503418,
    "specimen_id": 593312584,
    "stimulus_absolute_amplitude": 39.9999998401679,
    "stimulus_description": "C1LSFINEST150112[0]",
    "stimulus_duration": 0.99998,
    "stimulus_interval": null,
    "stimulus_name": "Long Square",
    "stimulus_relative_amplitude": 10.0,
    "stimulus_start_time": 1.02,
    "stimulus_units": "pA",
    "sweep_number": 38,
    "vm_delta_mv": 0.153327941894531
  },
  {
    "bridge_balance_mohm": 10.9890108108521,
    "id": 593322940,
    "leak_pa": 0.506489396095276,
    "num_spikes": 1,
    "peak_deflection": null,
    "post_noise_rms_mv": 0.0523641481995583,
    "post_vm_mv": -67.7789688110352,
    "pre_noise_rms_mv": 0.0341175012290478,
    "pre_vm_mv": -68.1574401855469,
    "slow_noise_rms_mv": 0.135288938879967,
    "slow_vm_mv": -68.1574401855469,
    "specimen_id": 593312584,
    "stimulus_absolute_amplitude": 39.9999998401679,
    "stimulus_description": "C1LSFINEST150112[0]",
    "stimulus_duration": 0.99998,
    "stimulus_interval": null,
    "stimulus_name": "Long Square",
    "stimulus_relative_amplitude": 10.0,
    "stimulus_start_time": 1.02,
    "stimulus_units": "pA",
    "sweep_number": 39,
    "vm_delta_mv": 0.378471374511719
  },
  {
    "bridge_balance_mohm": 10.9890108108521,
    "id": 593322952,
    "leak_pa": 0.506489396095276,
    "num_spikes": 1,
    "peak_deflection": null,
    "post_noise_rms_mv": 0.0556673631072044,
    "post_vm_mv": -68.0642242431641,
    "pre_noise_rms_mv": 0.044710036367178,
    "pre_vm_mv": -67.9546203613281,
    "slow_noise_rms_mv": 0.203024327754974,
    "slow_vm_mv": -67.9546203613281,
    "specimen_id": 593312584,
    "stimulus_absolute_amplitude": 39.9999998401679,
    "stimulus_description": "C1LSFINEST150112[0]",
    "stimulus_duration": 0.99998,
    "stimulus_interval": null,
    "stimulus_name": "Long Square",
    "stimulus_relative_amplitude": 10.0,
    "stimulus_start_time": 1.02,
    "stimulus_units": "pA",
    "sweep_number": 37,
    "vm_delta_mv": 0.109603881835938
  },
  {
    "bridge_balance_mohm": 10.9890108108521,
    "id": 593322894,
    "leak_pa": 1.45615696907043,
    "num_spikes": null,
    "peak_deflection": null,
    "post_noise_rms_mv": 0.0391889400780201,
    "post_vm_mv": -68.59130859375,
    "pre_noise_rms_mv": 0.0372342690825462,
    "pre_vm_mv": -68.4835662841797,
    "slow_noise_rms_mv": 0.125669941306114,
    "slow_vm_mv": -68.4835662841797,
    "specimen_id": 593312584,
    "stimulus_absolute_amplitude": 220.000004325094,
    "stimulus_description": "C1SSFINEST150112[0]",
    "stimulus_duration": 0.00298,
    "stimulus_interval": null,
    "stimulus_name": "Short Square",
    "stimulus_relative_amplitude": 10.0,
    "stimulus_start_time": 1.02,
    "stimulus_units": "pA",
    "sweep_number": 13,
    "vm_delta_mv": 0.107742309570312
  },
  {
    "bridge_balance_mohm": 10.9890108108521,
    "id": 593322956,
    "leak_pa": 1.26622343063354,
    "num_spikes": 35,
    "peak_deflection": null,
    "post_noise_rms_mv": 0.0431107804179192,
    "post_vm_mv": -68.7616424560547,
    "pre_noise_rms_mv": 0.0267597511410713,
    "pre_vm_mv": -67.8780822753906,
    "slow_noise_rms_mv": 0.163429394364357,
    "slow_vm_mv": -67.8780822753906,
    "specimen_id": 593312584,
    "stimulus_absolute_amplitude": 170.000000188075,
    "stimulus_description": "C1LSCOARSE150216[14]",
    "stimulus_duration": 0.99998,
    "stimulus_interval": null,
    "stimulus_name": "Long Square",
    "stimulus_relative_amplitude": 10.0,
    "stimulus_start_time": 1.02,
    "stimulus_units": "pA",
    "sweep_number": 35,
    "vm_delta_mv": 0.883560180664062
  },
  {
    "bridge_balance_mohm": 10.9890108108521,
    "id": 593322980,
    "leak_pa": -10.1930990219116,
    "num_spikes": null,
    "peak_deflection": null,
    "post_noise_rms_mv": 0.048114225268364,
    "post_vm_mv": -67.9503936767578,
    "pre_noise_rms_mv": 0.0352230928838253,
    "pre_vm_mv": -67.861701965332,
    "slow_noise_rms_mv": 0.477983027696609,
    "slow_vm_mv": -67.861701965332,
    "specimen_id": 593312584,
    "stimulus_absolute_amplitude": -200.000002670286,
    "stimulus_description": "C1SQCAPCHK141203[0]",
    "stimulus_duration": 7.21848,
    "stimulus_interval": 0.2005,
    "stimulus_name": "Square - 0.5ms Subthreshold",
    "stimulus_relative_amplitude": 10.0,
    "stimulus_start_time": 0.8215,
    "stimulus_units": "pA",
    "sweep_number": 58,
    "vm_delta_mv": 0.0886917114257812
  },
  {
    "bridge_balance_mohm": 10.9890108108521,
    "id": 593322986,
    "leak_pa": -2.78569149971008,
    "num_spikes": 44,
    "peak_deflection": null,
    "post_noise_rms_mv": 0.0438986718654633,
    "post_vm_mv": -68.0299835205078,
    "pre_noise_rms_mv": 0.048231840133667,
    "pre_vm_mv": -67.7321472167969,
    "slow_noise_rms_mv": 0.147458851337433,
    "slow_vm_mv": -67.7321472167969,
    "specimen_id": 593312584,
    "stimulus_absolute_amplitude": 92.7500021230543,
    "stimulus_description": "C1NSSEED_1150112[0]",
    "stimulus_duration": 18.99998,
    "stimulus_interval": 8.0,
    "stimulus_name": "Noise 1",
    "stimulus_relative_amplitude": 10.0,
    "stimulus_start_time": 2.02,
    "stimulus_units": "pA",
    "sweep_number": 51,
    "vm_delta_mv": 0.297836303710938
  },
  {
    "bridge_balance_mohm": null,
    "id": 593322922,
    "leak_pa": null,
    "num_spikes": null,
    "peak_deflection": null,
    "post_noise_rms_mv": null,
    "post_vm_mv": null,
    "pre_noise_rms_mv": null,
    "pre_vm_mv": null,
    "slow_noise_rms_mv": null,
    "slow_vm_mv": null,
    "specimen_id": 593312584,
    "stimulus_absolute_amplitude": null,
    "stimulus_description": "EXTPSMOKET141203[0]",
    "stimulus_duration": null,
    "stimulus_interval": null,
    "stimulus_name": "Test",
    "stimulus_relative_amplitude": 0.5,
    "stimulus_start_time": null,
    "stimulus_units": "mV",
    "sweep_number": 0,
    "vm_delta_mv": null
  },
  {
    "bridge_balance_mohm": 10.9890108108521,
    "id": 593322836,
    "leak_pa": -0.316555857658386,
    "num_spikes": 39,
    "peak_deflection": null,
    "post_noise_rms_mv": 0.0432330891489983,
    "post_vm_mv": -68.4637680053711,
    "pre_noise_rms_mv": 0.0391961894929409,
    "pre_vm_mv": -68.0567932128906,
    "slow_noise_rms_mv": 0.173092871904373,
    "slow_vm_mv": -68.0567932128906,
    "specimen_id": 593312584,
    "stimulus_absolute_amplitude": 92.7500021230543,
    "stimulus_description": "C1NSSEED_1150112[0]",
    "stimulus_duration": 18.99998,
    "stimulus_interval": 8.0,
    "stimulus_name": "Noise 1",
    "stimulus_relative_amplitude": 10.0,
    "stimulus_start_time": 2.02,
    "stimulus_units": "pA",
    "sweep_number": 45,
    "vm_delta_mv": 0.406974792480469
  },
  {
    "bridge_balance_mohm": 10.9890108108521,
    "id": 593322878,
    "leak_pa": -11.0161447525024,
    "num_spikes": 3,
    "peak_deflection": null,
    "post_noise_rms_mv": 0.0412486679852009,
    "post_vm_mv": -68.3102645874023,
    "pre_noise_rms_mv": 0.0421832017600536,
    "pre_vm_mv": -67.7890396118164,
    "slow_noise_rms_mv": 0.224258035421371,
    "slow_vm_mv": -67.7890396118164,
    "specimen_id": 593312584,
    "stimulus_absolute_amplitude": 230.000005152498,
    "stimulus_description": "C2SSTRIPLE150429[4]",
    "stimulus_duration": 0.04898,
    "stimulus_interval": 0.023,
    "stimulus_name": "Short Square - Triple",
    "stimulus_relative_amplitude": 10.0,
    "stimulus_start_time": 2.02,
    "stimulus_units": "pA",
    "sweep_number": 68,
    "vm_delta_mv": 0.521224975585938
  },
  {
    "bridge_balance_mohm": 10.9890108108521,
    "id": 593322856,
    "leak_pa": -11.0161447525024,
    "num_spikes": 3,
    "peak_deflection": null,
    "post_noise_rms_mv": 0.0307619627565145,
    "post_vm_mv": -67.9266052246094,
    "pre_noise_rms_mv": 0.0365618020296097,
    "pre_vm_mv": -67.8111877441406,
    "slow_noise_rms_mv": 0.160407617688179,
    "slow_vm_mv": -67.8111877441406,
    "specimen_id": 593312584,
    "stimulus_absolute_amplitude": 230.000005152498,
    "stimulus_description": "C2SSTRIPLE150429[6]",
    "stimulus_duration": 0.01898,
    "stimulus_interval": 0.008,
    "stimulus_name": "Short Square - Triple",
    "stimulus_relative_amplitude": 10.0,
    "stimulus_start_time": 2.02,
    "stimulus_units": "pA",
    "sweep_number": 70,
    "vm_delta_mv": 0.11541748046875
  },
  {
    "bridge_balance_mohm": 10.9890108108521,
    "id": 593322822,
    "leak_pa": -2.0259575843811,
    "num_spikes": 37,
    "peak_deflection": null,
    "post_noise_rms_mv": 0.0500451289117336,
    "post_vm_mv": -68.6159820556641,
    "pre_noise_rms_mv": 0.0369173623621464,
    "pre_vm_mv": -68.027458190918,
    "slow_noise_rms_mv": 0.130467861890793,
    "slow_vm_mv": -68.027458190918,
    "specimen_id": 593312584,
    "stimulus_absolute_amplitude": 94.2499966960497,
    "stimulus_description": "C1NSSEED_2150112[0]",
    "stimulus_duration": 18.99998,
    "stimulus_interval": 8.0,
    "stimulus_name": "Noise 2",
    "stimulus_relative_amplitude": 10.0,
    "stimulus_start_time": 2.02,
    "stimulus_units": "pA",
    "sweep_number": 48,
    "vm_delta_mv": 0.588523864746094
  },
  {
    "bridge_balance_mohm": 10.9890108108521,
    "id": 593322898,
    "leak_pa": 2.21589112281799,
    "num_spikes": null,
    "peak_deflection": null,
    "post_noise_rms_mv": 0.0403630025684834,
    "post_vm_mv": -68.3690567016602,
    "pre_noise_rms_mv": 0.0409322716295719,
    "pre_vm_mv": -68.2636871337891,
    "slow_noise_rms_mv": 0.0996251925826073,
    "slow_vm_mv": -68.2636871337891,
    "specimen_id": 593312584,
    "stimulus_absolute_amplitude": 230.000005152498,
    "stimulus_description": "C1SSFINEST150112[0]",
    "stimulus_duration": 0.00298,
    "stimulus_interval": null,
    "stimulus_name": "Short Square",
    "stimulus_relative_amplitude": 10.0,
    "stimulus_start_time": 1.02,
    "stimulus_units": "pA",
    "sweep_number": 19,
    "vm_delta_mv": 0.105369567871094
  },
  {
    "bridge_balance_mohm": 10.9890108108521,
    "id": 593322838,
    "leak_pa": 0.506489396095276,
    "num_spikes": 13,
    "peak_deflection": null,
    "post_noise_rms_mv": 0.0363569781184196,
    "post_vm_mv": -68.4527740478516,
    "pre_noise_rms_mv": 0.032952394336462,
    "pre_vm_mv": -68.0785064697266,
    "slow_noise_rms_mv": 0.167171224951744,
    "slow_vm_mv": -68.0785064697266,
    "specimen_id": 593312584,
    "stimulus_absolute_amplitude": 79.9999996803358,
    "stimulus_description": "C1LSFINEST150112[0]",
    "stimulus_duration": 0.99998,
    "stimulus_interval": null,
    "stimulus_name": "Long Square",
    "stimulus_relative_amplitude": 10.0,
    "stimulus_start_time": 1.02,
    "stimulus_units": "pA",
    "sweep_number": 44,
    "vm_delta_mv": 0.374267578125
  },
  {
    "bridge_balance_mohm": 10.9890108108521,
    "id": 593322916,
    "leak_pa": -11.0161447525024,
    "num_spikes": 3,
    "peak_deflection": null,
    "post_noise_rms_mv": 0.032310351729393,
    "post_vm_mv": -67.6327972412109,
    "pre_noise_rms_mv": 0.0336076132953167,
    "pre_vm_mv": -67.5331649780273,
    "slow_noise_rms_mv": 0.235483154654503,
    "slow_vm_mv": -67.5331649780273,
    "specimen_id": 593312584,
    "stimulus_absolute_amplitude": 230.000005152498,
    "stimulus_description": "C2SSTRIPLE150429[2]",
    "stimulus_duration": 0.16898,
    "stimulus_interval": 0.083,
    "stimulus_name": "Short Square - Triple",
    "stimulus_relative_amplitude": 10.0,
    "stimulus_start_time": 2.02,
    "stimulus_units": "pA",
    "sweep_number": 80,
    "vm_delta_mv": 0.0996322631835938
  },
  {
    "bridge_balance_mohm": null,
    "id": 593322918,
    "leak_pa": null,
    "num_spikes": null,
    "peak_deflection": null,
    "post_noise_rms_mv": null,
    "post_vm_mv": null,
    "pre_noise_rms_mv": null,
    "pre_vm_mv": null,
    "slow_noise_rms_mv": null,
    "slow_vm_mv": null,
    "specimen_id": 593312584,
    "stimulus_absolute_amplitude": null,
    "stimulus_description": "EXTPCllATT141203[0]",
    "stimulus_duration": null,
    "stimulus_interval": null,
    "stimulus_name": "Test",
    "stimulus_relative_amplitude": 0.5,
    "stimulus_start_time": null,
    "stimulus_units": "mV",
    "sweep_number": 2,
    "vm_delta_mv": null
  },
  {
    "bridge_balance_mohm": 10.9890108108521,
    "id": 593322880,
    "leak_pa": 1.45615696907043,
    "num_spikes": 1,
    "peak_deflection": null,
    "post_noise_rms_mv": 0.0453574471175671,
    "post_vm_mv": -69.2111892700195,
    "pre_noise_rms_mv": 0.04123380407691,
    "pre_vm_mv": -68.8540420532227,
    "slow_noise_rms_mv": 0.129006147384644,
    "slow_vm_mv": -68.8540420532227,
    "specimen_id": 593312584,
    "stimulus_absolute_amplitude": 230.000005152498,
    "stimulus_description": "C1SSFINEST150112[0]",
    "stimulus_duration": 0.00298,
    "stimulus_interval": null,
    "stimulus_name": "Short Square",
    "stimulus_relative_amplitude": 10.0,
    "stimulus_start_time": 1.02,
    "stimulus_units": "pA",
    "sweep_number": 14,
    "vm_delta_mv": 0.357147216796875
  },
  {
    "bridge_balance_mohm": 10.9890108108521,
    "id": 593322870,
    "leak_pa": -11.0161447525024,
    "num_spikes": 3,
    "peak_deflection": null,
    "post_noise_rms_mv": 0.0631227865815163,
    "post_vm_mv": -68.9039764404297,
    "pre_noise_rms_mv": 0.0445864237844944,
    "pre_vm_mv": -68.5989608764648,
    "slow_noise_rms_mv": 0.284824252128601,
    "slow_vm_mv": -68.5989608764648,
    "specimen_id": 593312584,
    "stimulus_absolute_amplitude": 230.000005152498,
    "stimulus_description": "C2SSTRIPLE150429[0]",
    "stimulus_duration": 0.64898,
    "stimulus_interval": 0.323,
    "stimulus_name": "Short Square - Triple",
    "stimulus_relative_amplitude": 10.0,
    "stimulus_start_time": 2.02,
    "stimulus_units": "pA",
    "sweep_number": 64,
    "vm_delta_mv": 0.305015563964844
  },
  {
    "bridge_balance_mohm": null,
    "id": 593322920,
    "leak_pa": null,
    "num_spikes": null,
    "peak_deflection": null,
    "post_noise_rms_mv": null,
    "post_vm_mv": null,
    "pre_noise_rms_mv": null,
    "pre_vm_mv": null,
    "slow_noise_rms_mv": null,
    "slow_vm_mv": null,
    "specimen_id": 593312584,
    "stimulus_absolute_amplitude": null,
    "stimulus_description": "EXTPBREAKN141203[0]",
    "stimulus_duration": null,
    "stimulus_interval": null,
    "stimulus_name": "Test",
    "stimulus_relative_amplitude": 0.5,
    "stimulus_start_time": null,
    "stimulus_units": "mV",
    "sweep_number": 3,
    "vm_delta_mv": null
  },
  {
    "bridge_balance_mohm": 10.9890108108521,
    "id": 593322882,
    "leak_pa": 2.21589112281799,
    "num_spikes": 1,
    "peak_deflection": null,
    "post_noise_rms_mv": 0.0271435379981995,
    "post_vm_mv": -68.969856262207,
    "pre_noise_rms_mv": 0.0373516790568829,
    "pre_vm_mv": -68.5627288818359,
    "slow_noise_rms_mv": 0.118298225104809,
    "slow_vm_mv": -68.5627288818359,
    "specimen_id": 593312584,
    "stimulus_absolute_amplitude": 230.000005152498,
    "stimulus_description": "C1SSFINEST150112[0]",
    "stimulus_duration": 0.00298,
    "stimulus_interval": null,
    "stimulus_name": "Short Square",
    "stimulus_relative_amplitude": 10.0,
    "stimulus_start_time": 1.02,
    "stimulus_units": "pA",
    "sweep_number": 15,
    "vm_delta_mv": 0.407127380371094
  },
  {
    "bridge_balance_mohm": 10.9890108108521,
    "id": 593322874,
    "leak_pa": -11.0161447525024,
    "num_spikes": 3,
    "peak_deflection": null,
    "post_noise_rms_mv": 0.034825935959816,
    "post_vm_mv": -68.8682174682617,
    "pre_noise_rms_mv": 0.0418457500636578,
    "pre_vm_mv": -68.0478363037109,
    "slow_noise_rms_mv": 0.135853826999664,
    "slow_vm_mv": -68.0478363037109,
    "specimen_id": 593312584,
    "stimulus_absolute_amplitude": 230.000005152498,
    "stimulus_description": "C2SSTRIPLE150429[2]",
    "stimulus_duration": 0.16898,
    "stimulus_interval": 0.083,
    "stimulus_name": "Short Square - Triple",
    "stimulus_relative_amplitude": 10.0,
    "stimulus_start_time": 2.02,
    "stimulus_units": "pA",
    "sweep_number": 66,
    "vm_delta_mv": 0.820381164550781
  },
  {
    "bridge_balance_mohm": 10.9890108108521,
    "id": 593322824,
    "leak_pa": 0.506489396095276,
    "num_spikes": 14,
    "peak_deflection": null,
    "post_noise_rms_mv": 0.0456363894045353,
    "post_vm_mv": -68.4717330932617,
    "pre_noise_rms_mv": 0.0443003289401531,
    "pre_vm_mv": -67.7271347045898,
    "slow_noise_rms_mv": 0.184892505407333,
    "slow_vm_mv": -67.7271347045898,
    "specimen_id": 593312584,
    "stimulus_absolute_amplitude": 79.9999996803358,
    "stimulus_description": "C1LSFINEST150112[0]",
    "stimulus_duration": 0.99998,
    "stimulus_interval": null,
    "stimulus_name": "Long Square",
    "stimulus_relative_amplitude": 10.0,
    "stimulus_start_time": 1.02,
    "stimulus_units": "pA",
    "sweep_number": 43,
    "vm_delta_mv": 0.744598388671875
  },
  {
    "bridge_balance_mohm": 10.9890108108521,
    "id": 593322968,
    "leak_pa": 1.26622343063354,
    "num_spikes": null,
    "peak_deflection": -74.0312576293945,
    "post_noise_rms_mv": 0.0350718423724174,
    "post_vm_mv": -68.1426773071289,
    "pre_noise_rms_mv": 0.0421840958297253,
    "pre_vm_mv": -67.8452301025391,
    "slow_noise_rms_mv": 0.139870449900627,
    "slow_vm_mv": -67.8452301025391,
    "specimen_id": 593312584,
    "stimulus_absolute_amplitude": -9.99999996004197,
    "stimulus_description": "C1LSCOARSE150216[5]",
    "stimulus_duration": 0.99998,
    "stimulus_interval": null,
    "stimulus_name": "Long Square",
    "stimulus_relative_amplitude": 10.0,
    "stimulus_start_time": 1.02,
    "stimulus_units": "pA",
    "sweep_number": 26,
    "vm_delta_mv": 0.297447204589844
  },
  {
    "bridge_balance_mohm": 10.9890108108521,
    "id": 593322936,
    "leak_pa": 3.22886991500854,
    "num_spikes": 1,
    "peak_deflection": null,
    "post_noise_rms_mv": 0.0507641769945621,
    "post_vm_mv": -67.5378036499023,
    "pre_noise_rms_mv": 0.0458601266145706,
    "pre_vm_mv": -67.087158203125,
    "slow_noise_rms_mv": 0.285382002592087,
    "slow_vm_mv": -67.087158203125,
    "specimen_id": 593312584,
    "stimulus_absolute_amplitude": 299.999997066536,
    "stimulus_description": "C1SSCOARSE150112[2]",
    "stimulus_duration": 0.00298,
    "stimulus_interval": null,
    "stimulus_name": "Short Square",
    "stimulus_relative_amplitude": 10.0,
    "stimulus_start_time": 1.02,
    "stimulus_units": "pA",
    "sweep_number": 9,
    "vm_delta_mv": 0.450645446777344
  },
  {
    "bridge_balance_mohm": 10.9890108108521,
    "id": 593322830,
    "leak_pa": 0.506489396095276,
    "num_spikes": 1,
    "peak_deflection": null,
    "post_noise_rms_mv": 0.0402902811765671,
    "post_vm_mv": -68.1349334716797,
    "pre_noise_rms_mv": 0.0354429222643375,
    "pre_vm_mv": -68.3135528564453,
    "slow_noise_rms_mv": 0.195098221302032,
    "slow_vm_mv": -68.3135528564453,
    "specimen_id": 593312584,
    "stimulus_absolute_amplitude": 39.9999998401679,
    "stimulus_description": "C1LSFINEST150112[0]",
    "stimulus_duration": 0.99998,
    "stimulus_interval": null,
    "stimulus_name": "Long Square",
    "stimulus_relative_amplitude": 10.0,
    "stimulus_start_time": 1.02,
    "stimulus_units": "pA",
    "sweep_number": 40,
    "vm_delta_mv": 0.178619384765625
  },
  {
    "bridge_balance_mohm": null,
    "id": 593322902,
    "leak_pa": null,
    "num_spikes": null,
    "peak_deflection": null,
    "post_noise_rms_mv": 0.0384734682738781,
    "post_vm_mv": 3.76065874099731,
    "pre_noise_rms_mv": 0.0401732549071312,
    "pre_vm_mv": 3.73179030418396,
    "slow_noise_rms_mv": 0.0495210811495781,
    "slow_vm_mv": 3.73179030418396,
    "specimen_id": 593312584,
    "stimulus_absolute_amplitude": 0.0,
    "stimulus_description": "EXTPBLWOUT141203[0]",
    "stimulus_duration": 0.0,
    "stimulus_interval": null,
    "stimulus_name": "Test",
    "stimulus_relative_amplitude": 10.0,
    "stimulus_start_time": 0.0,
    "stimulus_units": "pA",
    "sweep_number": 87,
    "vm_delta_mv": 0.0288684368133545
  },
  {
    "bridge_balance_mohm": 10.9890108108521,
    "id": 593322834,
    "leak_pa": -0.316555857658386,
    "num_spikes": 39,
    "peak_deflection": null,
    "post_noise_rms_mv": 0.0418866090476513,
    "post_vm_mv": -68.2531509399414,
    "pre_noise_rms_mv": 0.0423577763140202,
    "pre_vm_mv": -67.7761077880859,
    "slow_noise_rms_mv": 0.12779726088047,
    "slow_vm_mv": -67.7761077880859,
    "specimen_id": 593312584,
    "stimulus_absolute_amplitude": 94.2499966960497,
    "stimulus_description": "C1NSSEED_2150112[0]",
    "stimulus_duration": 18.99998,
    "stimulus_interval": 8.0,
    "stimulus_name": "Noise 2",
    "stimulus_relative_amplitude": 10.0,
    "stimulus_start_time": 2.02,
    "stimulus_units": "pA",
    "sweep_number": 46,
    "vm_delta_mv": 0.477043151855469
  },
  {
    "bridge_balance_mohm": null,
    "id": 593322900,
    "leak_pa": null,
    "num_spikes": null,
    "peak_deflection": null,
    "post_noise_rms_mv": 0.0351682864129543,
    "post_vm_mv": 3.60922241210938,
    "pre_noise_rms_mv": 0.0387881025671959,
    "pre_vm_mv": 3.60681366920471,
    "slow_noise_rms_mv": 0.0452624931931496,
    "slow_vm_mv": 3.60681366920471,
    "specimen_id": 593312584,
    "stimulus_absolute_amplitude": 0.0,
    "stimulus_description": "EXTPBLWOUT141203[0]",
    "stimulus_duration": 0.0,
    "stimulus_interval": null,
    "stimulus_name": "Test",
    "stimulus_relative_amplitude": 10.0,
    "stimulus_start_time": 0.0,
    "stimulus_units": "pA",
    "sweep_number": 88,
    "vm_delta_mv": 0.00240874290466309
  },
  {
    "bridge_balance_mohm": 10.9890108108521,
    "id": 593322858,
    "leak_pa": -11.0161447525024,
    "num_spikes": 3,
    "peak_deflection": null,
    "post_noise_rms_mv": 0.036902841180563,
    "post_vm_mv": -67.1680221557617,
    "pre_noise_rms_mv": 0.0379601866006851,
    "pre_vm_mv": -67.1740875244141,
    "slow_noise_rms_mv": 0.133777603507042,
    "slow_vm_mv": -67.1740875244141,
    "specimen_id": 593312584,
    "stimulus_absolute_amplitude": 230.000005152498,
    "stimulus_description": "C2SSTRIPLE150429[0]",
    "stimulus_duration": 0.64898,
    "stimulus_interval": 0.323,
    "stimulus_name": "Short Square - Triple",
    "stimulus_relative_amplitude": 10.0,
    "stimulus_start_time": 2.02,
    "stimulus_units": "pA",
    "sweep_number": 71,
    "vm_delta_mv": 0.00606536865234375
  },
  {
    "bridge_balance_mohm": 10.9890108108521,
    "id": 593322868,
    "leak_pa": -11.0161447525024,
    "num_spikes": 3,
    "peak_deflection": null,
    "post_noise_rms_mv": 0.0511174611747265,
    "post_vm_mv": -68.8863983154297,
    "pre_noise_rms_mv": 0.0381728932261467,
    "pre_vm_mv": -68.5782165527344,
    "slow_noise_rms_mv": 0.198939844965935,
    "slow_vm_mv": -68.5782165527344,
    "specimen_id": 593312584,
    "stimulus_absolute_amplitude": 230.000005152498,
    "stimulus_description": "C2SSTRIPLE150429[1]",
    "stimulus_duration": 0.32898,
    "stimulus_interval": 0.163,
    "stimulus_name": "Short Square - Triple",
    "stimulus_relative_amplitude": 10.0,
    "stimulus_start_time": 2.02,
    "stimulus_units": "pA",
    "sweep_number": 65,
    "vm_delta_mv": 0.308181762695312
  },
  {
    "bridge_balance_mohm": 10.9890108108521,
    "id": 593322910,
    "leak_pa": -11.0161447525024,
    "num_spikes": 3,
    "peak_deflection": null,
    "post_noise_rms_mv": 0.0357127450406551,
    "post_vm_mv": -67.7138061523438,
    "pre_noise_rms_mv": 0.0492913983762264,
    "pre_vm_mv": -67.8130950927734,
    "slow_noise_rms_mv": 0.191253885626793,
    "slow_vm_mv": -67.8130950927734,
    "specimen_id": 593312584,
    "stimulus_absolute_amplitude": 230.000005152498,
    "stimulus_description": "C2SSTRIPLE150429[5]",
    "stimulus_duration": 0.02898,
    "stimulus_interval": 0.013,
    "stimulus_name": "Short Square - Triple",
    "stimulus_relative_amplitude": 10.0,
    "stimulus_start_time": 2.02,
    "stimulus_units": "pA",
    "sweep_number": 83,
    "vm_delta_mv": 0.0992889404296875
  },
  {
    "bridge_balance_mohm": 10.9890108108521,
    "id": 593322942,
    "leak_pa": 1.26622343063354,
    "num_spikes": 26,
    "peak_deflection": null,
    "post_noise_rms_mv": 0.0386942364275455,
    "post_vm_mv": -69.2275695800781,
    "pre_noise_rms_mv": 0.0370234772562981,
    "pre_vm_mv": -68.3627624511719,
    "slow_noise_rms_mv": 0.175101161003113,
    "slow_vm_mv": -68.3627624511719,
    "specimen_id": 593312584,
    "stimulus_absolute_amplitude": 110.000002162547,
    "stimulus_description": "C1LSCOARSE150216[11]",
    "stimulus_duration": 0.99998,
    "stimulus_interval": null,
    "stimulus_name": "Long Square",
    "stimulus_relative_amplitude": 10.0,
    "stimulus_start_time": 1.02,
    "stimulus_units": "pA",
    "sweep_number": 32,
    "vm_delta_mv": 0.86480712890625
  },
  {
    "bridge_balance_mohm": null,
    "id": 593322904,
    "leak_pa": null,
    "num_spikes": null,
    "peak_deflection": null,
    "post_noise_rms_mv": null,
    "post_vm_mv": null,
    "pre_noise_rms_mv": null,
    "pre_vm_mv": null,
    "slow_noise_rms_mv": null,
    "slow_vm_mv": null,
    "specimen_id": 593312584,
    "stimulus_absolute_amplitude": null,
    "stimulus_description": "EXTPGGAEND141203[0]",
    "stimulus_duration": null,
    "stimulus_interval": null,
    "stimulus_name": "Test",
    "stimulus_relative_amplitude": 0.5,
    "stimulus_start_time": null,
    "stimulus_units": "mV",
    "sweep_number": 86,
    "vm_delta_mv": null
  },
  {
    "bridge_balance_mohm": 10.9890108108521,
    "id": 593322876,
    "leak_pa": -11.0161447525024,
    "num_spikes": 3,
    "peak_deflection": null,
    "post_noise_rms_mv": 0.0426252149045467,
    "post_vm_mv": -68.1846237182617,
    "pre_noise_rms_mv": 0.0401094406843185,
    "pre_vm_mv": -68.5136871337891,
    "slow_noise_rms_mv": 0.264588415622711,
    "slow_vm_mv": -68.5136871337891,
    "specimen_id": 593312584,
    "stimulus_absolute_amplitude": 230.000005152498,
    "stimulus_description": "C2SSTRIPLE150429[5]",
    "stimulus_duration": 0.02898,
    "stimulus_interval": 0.013,
    "stimulus_name": "Short Square - Triple",
    "stimulus_relative_amplitude": 10.0,
    "stimulus_start_time": 2.02,
    "stimulus_units": "pA",
    "sweep_number": 69,
    "vm_delta_mv": 0.329063415527344
  },
  {
    "bridge_balance_mohm": 10.9890108108521,
    "id": 593322888,
    "leak_pa": 2.21589112281799,
    "num_spikes": 1,
    "peak_deflection": null,
    "post_noise_rms_mv": 0.0369020998477936,
    "post_vm_mv": -68.6931381225586,
    "pre_noise_rms_mv": 0.0437123067677021,
    "pre_vm_mv": -68.4571685791016,
    "slow_noise_rms_mv": 0.135873943567276,
    "slow_vm_mv": -68.4571685791016,
    "specimen_id": 593312584,
    "stimulus_absolute_amplitude": 249.999992929517,
    "stimulus_description": "C1SSFINEST150112[0]",
    "stimulus_duration": 0.00298,
    "stimulus_interval": null,
    "stimulus_name": "Short Square",
    "stimulus_relative_amplitude": 10.0,
    "stimulus_start_time": 1.02,
    "stimulus_units": "pA",
    "sweep_number": 10,
    "vm_delta_mv": 0.235969543457031
  },
  {
    "bridge_balance_mohm": 10.9890108108521,
    "id": 593322832,
    "leak_pa": -2.0259575843811,
    "num_spikes": 38,
    "peak_deflection": null,
    "post_noise_rms_mv": 0.0296553857624531,
    "post_vm_mv": -69.0143585205078,
    "pre_noise_rms_mv": 0.0406115353107452,
    "pre_vm_mv": -68.1167068481445,
    "slow_noise_rms_mv": 0.316859006881714,
    "slow_vm_mv": -68.1167068481445,
    "specimen_id": 593312584,
    "stimulus_absolute_amplitude": 92.7500021230543,
    "stimulus_description": "C1NSSEED_1150112[0]",
    "stimulus_duration": 18.99998,
    "stimulus_interval": 8.0,
    "stimulus_name": "Noise 1",
    "stimulus_relative_amplitude": 10.0,
    "stimulus_start_time": 2.02,
    "stimulus_units": "pA",
    "sweep_number": 47,
    "vm_delta_mv": 0.897651672363281
  },
  {
    "bridge_balance_mohm": 10.9890108108521,
    "id": 593322948,
    "leak_pa": 1.26622343063354,
    "num_spikes": 20,
    "peak_deflection": null,
    "post_noise_rms_mv": 0.0419079288840294,
    "post_vm_mv": -68.8302841186523,
    "pre_noise_rms_mv": 0.0376706831157207,
    "pre_vm_mv": -68.2666244506836,
    "slow_noise_rms_mv": 0.174076229333878,
    "slow_vm_mv": -68.2666244506836,
    "specimen_id": 593312584,
    "stimulus_absolute_amplitude": 90.0000005077395,
    "stimulus_description": "C1LSCOARSE150216[10]",
    "stimulus_duration": 0.99998,
    "stimulus_interval": null,
    "stimulus_name": "Long Square",
    "stimulus_relative_amplitude": 10.0,
    "stimulus_start_time": 1.02,
    "stimulus_units": "pA",
    "sweep_number": 31,
    "vm_delta_mv": 0.56365966796875
  },
  {
    "bridge_balance_mohm": 10.9890108108521,
    "id": 593322846,
    "leak_pa": -11.0161447525024,
    "num_spikes": 3,
    "peak_deflection": null,
    "post_noise_rms_mv": 0.044875405728817,
    "post_vm_mv": -67.8769683837891,
    "pre_noise_rms_mv": 0.0380422472953796,
    "pre_vm_mv": -67.5977172851562,
    "slow_noise_rms_mv": 0.132297649979591,
    "slow_vm_mv": -67.5977172851562,
    "specimen_id": 593312584,
    "stimulus_absolute_amplitude": 230.000005152498,
    "stimulus_description": "C2SSTRIPLE150429[6]",
    "stimulus_duration": 0.01898,
    "stimulus_interval": 0.008,
    "stimulus_name": "Short Square - Triple",
    "stimulus_relative_amplitude": 10.0,
    "stimulus_start_time": 2.02,
    "stimulus_units": "pA",
    "sweep_number": 77,
    "vm_delta_mv": 0.279251098632812
  },
  {
    "bridge_balance_mohm": 10.9890108108521,
    "id": 593322850,
    "leak_pa": -11.0161447525024,
    "num_spikes": 3,
    "peak_deflection": null,
    "post_noise_rms_mv": 0.0385285764932632,
    "post_vm_mv": -68.4816436767578,
    "pre_noise_rms_mv": 0.0433297120034695,
    "pre_vm_mv": -67.7226028442383,
    "slow_noise_rms_mv": 0.293877929449081,
    "slow_vm_mv": -67.7226028442383,
    "specimen_id": 593312584,
    "stimulus_absolute_amplitude": 230.000005152498,
    "stimulus_description": "C2SSTRIPLE150429[4]",
    "stimulus_duration": 0.04898,
    "stimulus_interval": 0.023,
    "stimulus_name": "Short Square - Triple",
    "stimulus_relative_amplitude": 10.0,
    "stimulus_start_time": 2.02,
    "stimulus_units": "pA",
    "sweep_number": 75,
    "vm_delta_mv": 0.759040832519531
  }
]